<odoo>
    <data noupdate="0">
        <record id="email_margen_indaws" model="mail.template">
            <field name="name">Email Margen Ventas</field>
            <field name="use_default_to" eval="False"/>
            <field name="email_to">${object.get_emails()}</field>
            <field name="subject">presupuesto ${object.name}</field>
            <field name="model_id" ref="sale.model_sale_order" />
            <field name="partner_to" >${object.partner_id.id}</field>
<!--            <field name="report_name">${object.filename}</field>-->
            <field name="auto_delete" eval="False"/>
            <field name="body_html"><![CDATA[
                <div>
                    <p>
                        Estimado responsable de compras,</br></br>
                        En el presupuesto/pedido ${object.name}, se ha modificado el precio de los productos saltándose el margen establecido.</br></br>
                        Para que quede constancia.</br></br>
                        Gracias.
                    </p>
                </div>
            ]]>
            </field>
        </record>
    </data>
</odoo>